qrgenkit/__init__.py
qrgenkit/generators/__init__.py
qrgenkit/generators/base_generator.py
qrgenkit/generators/list_generator.py
qrgenkit/generators/range_generator.py
qrgenkit/generators/single_generator.py
qrgenkit/qr/__init__.py
qrgenkit/qr/qr_config.py
qrgenkit/qr/qr_generator.py
qrgenkit-0.1.0.dist-info/licenses/LICENSE
qrgenkit-0.1.0.dist-info/METADATA
qrgenkit-0.1.0.dist-info/WHEEL
qrgenkit-0.1.0.dist-info/top_level.txt
qrgenkit-0.1.0.dist-info/RECORD
