Metadata-Version: 2.4
Name: qrgenkit
Version: 0.1.0
Summary: A simple QR code generation utility with list, range, and single generators.
Author-email: Manthan Khandale <manthankhandale@gmail.com>
License-Expression: MIT
Project-URL: Homepage, https://github.com/Manty-K/qrgenkit
Project-URL: Issues, https://github.com/Manty-K/qrgenkit/issues
Requires-Python: >=3.10
License-File: LICENSE
Requires-Dist: pillow==12.0.0
Requires-Dist: qrcode==8.2
Dynamic: license-file
